flickrhistory/__init__.py
flickrhistory/__main__.py
flickrhistory/apikeymanager.py
flickrhistory/basicflickrhistorydownloader.py
flickrhistory/cache.py
flickrhistory/cacheupdaterthread.py
flickrhistory/config.py
flickrhistory/exceptions.py
flickrhistory/fancyflickrhistorydownloader.py
flickrhistory/flickrhistorydownloader.py
flickrhistory/licensedownloader.py
flickrhistory/photodownloader.py
flickrhistory/photodownloaderthread.py
flickrhistory/photoupdater.py
flickrhistory/photoupdaterthread.py
flickrhistory/sigtermreceivedexception.py
flickrhistory/timeoutlock.py
flickrhistory/timespan.py
flickrhistory/userprofiledownloader.py
flickrhistory/userprofileupdaterthread.py
flickrhistory/database/__init__.py
flickrhistory/database/databaseschemaupdater.py
flickrhistory/database/photo_saver.py
flickrhistory/database/session.py
flickrhistory/database/user_saver.py
flickrhistory/database/models/__init__.py
flickrhistory/database/models/base.py
flickrhistory/database/models/license.py
flickrhistory/database/models/photo.py
flickrhistory/database/models/tag.py
flickrhistory/database/models/user.py
flickrhistory-0.3.1.dist-info/licenses/LICENSE
flickrhistory-0.3.1.dist-info/METADATA
flickrhistory-0.3.1.dist-info/WHEEL
flickrhistory-0.3.1.dist-info/top_level.txt
flickrhistory-0.3.1.dist-info/RECORD
