Metadata-Version: 2.4
Name: flickrhistory
Version: 0.3.1
Summary: Download a complete history of georeferenced flickr posts
Author: Christoph Fink, Tatu Leppämäki
License: GPL-3.0-or-later
Project-URL: Repository, https://github.com/DigitalGeographyLab/flickrhistory/
Project-URL: Change Log, https://github.com/DigitalGeographyLab/flickrhistory/blob/main/CHANGELOG.md
Project-URL: Bug tracker, https://github.com/DigitalGeographyLab/flickrhistory/issues
Keywords: social media,API,flickr,image,photo,download
Classifier: Programming Language :: Python :: 3
Classifier: License :: OSI Approved :: GNU General Public License v3 (GPLv3)
Classifier: Operating System :: OS Independent
Requires-Python: >=3.10
License-File: LICENSE
Requires-Dist: blessed
Requires-Dist: GeoAlchemy2
Requires-Dist: PyYaml
Requires-Dist: psycopg2
Requires-Dist: requests
Requires-Dist: SQLAlchemy
Requires-Dist: urllib3
Dynamic: license-file
